POKE_DONPOLLO/__init__.py
POKE_DONPOLLO/pokemon.csv
POKE_DONPOLLO/ramdom_pokemon.py
pokelocopollo-2.0.0.dist-info/METADATA
pokelocopollo-2.0.0.dist-info/WHEEL
pokelocopollo-2.0.0.dist-info/top_level.txt
pokelocopollo-2.0.0.dist-info/RECORD
