Metadata-Version: 2.1
Name: pokelocopollo
Version: 2.0.0
Summary: LIBRERIA QUE GENRA UN POKEMON DE DONPOLLOLO, ES DECIR UN POKEMON ALEATORIO
Author: FernandoRoldan
Author-email: roldanf661@gmail.com
Requires-Dist: pandas
